ovos_PHAL_plugin_wallpaper_manager/__init__.py
ovos_PHAL_plugin_wallpaper_manager/version.py
ovos_PHAL_plugin_wallpaper_manager/wallpapers/background-01.png
ovos_PHAL_plugin_wallpaper_manager/wallpapers/background-02.png
ovos_PHAL_plugin_wallpaper_manager/wallpapers/background-03.png
ovos_PHAL_plugin_wallpaper_manager/wallpapers/background-04.png
ovos_PHAL_plugin_wallpaper_manager/wallpapers/background-05.png
ovos_PHAL_plugin_wallpaper_manager/wallpapers/default.jpg
ovos_phal_plugin_wallpaper_manager-0.2.6.dist-info/licenses/LICENSE
ovos_phal_plugin_wallpaper_manager-0.2.6.dist-info/METADATA
ovos_phal_plugin_wallpaper_manager-0.2.6.dist-info/WHEEL
ovos_phal_plugin_wallpaper_manager-0.2.6.dist-info/entry_points.txt
ovos_phal_plugin_wallpaper_manager-0.2.6.dist-info/top_level.txt
ovos_phal_plugin_wallpaper_manager-0.2.6.dist-info/zip-safe
ovos_phal_plugin_wallpaper_manager-0.2.6.dist-info/RECORD
