Metadata-Version: 2.4
Name: ovos_PHAL_plugin_wallpaper_manager
Version: 0.2.6
Summary: A plugin for OpenVoiceOS hardware abstraction layer
Home-page: https://github.com/OpenVoiceOS/ovos-PHAL-plugin-wallpaper-manager
Author: Aiix
Author-email: aix.m@outlook.com
License: Apache-2.0
Classifier: Development Status :: 3 - Alpha
Classifier: Intended Audience :: Developers
Classifier: Topic :: System :: Networking
Classifier: License :: OSI Approved :: Apache Software License
Classifier: Programming Language :: Python :: 3.5
Classifier: Programming Language :: Python :: 3.6
Classifier: Programming Language :: Python :: 3.7
Classifier: Programming Language :: Python :: 3.8
Classifier: Programming Language :: Python :: 3.9
Classifier: Programming Language :: Python :: 3.10
License-File: LICENSE
Requires-Dist: ovos-plugin-manager<3.0.0,>=0.0.23
Requires-Dist: ovos-utils<1.0.0,>=0.0.33
Requires-Dist: ovos_bus_client<2.0.0,>=0.0.3
Requires-Dist: wallpaper-finder
Dynamic: author
Dynamic: author-email
Dynamic: classifier
Dynamic: description
Dynamic: description-content-type
Dynamic: home-page
Dynamic: license
Dynamic: license-file
Dynamic: requires-dist
Dynamic: summary
